[
  {
    "url": "https://lantern.labaton.com/case/seatgeek",
    "title": "SeatGeek - Lantern",
    "description": "[email protected]",
    "potential_recovery": "$500 or more POTENTIAL RECOVERY",
    "eligible_states": "California, New York, and Virginia",
    "date": null,
    "scraped_at": "2025-12-03T21:22:53.365784",
    "source": "Lantern Labaton",
    "status": "Open to New Clients"
  },
  {
    "url": "https://lantern.labaton.com/case/albert",
    "title": "Albert - Lantern",
    "description": "[email protected]",
    "potential_recovery": "$500 or more POTENTIAL RECOVERY",
    "eligible_states": "California, New York, and Virginia",
    "date": null,
    "scraped_at": "2025-12-03T21:22:55.209953",
    "source": "Lantern Labaton",
    "status": "Open to New Clients"
  },
  {
    "url": "https://lantern.labaton.com/case/tilt",
    "title": "Tilt - Lantern",
    "description": "[email protected]",
    "potential_recovery": "$500 or more POTENTIAL RECOVERY",
    "eligible_states": "California, New York, and Virginia",
    "date": null,
    "scraped_at": "2025-12-03T21:22:57.063436",
    "source": "Lantern Labaton",
    "status": "Open to New Clients"
  },
  {
    "url": "https://lantern.labaton.com/case/klover",
    "title": "Klover - Lantern",
    "description": "[email protected]",
    "potential_recovery": "$500 or more POTENTIAL RECOVERY",
    "eligible_states": "California, New York, and Virginia",
    "date": null,
    "scraped_at": "2025-12-03T21:22:59.101685",
    "source": "Lantern Labaton",
    "status": "Open to New Clients"
  },
  {
    "url": "https://lantern.labaton.com/case/prosper",
    "title": "Prosper - Lantern",
    "description": "[email protected]",
    "potential_recovery": "$500 or more POTENTIAL RECOVERY",
    "eligible_states": "California, New York, and Virginia",
    "date": null,
    "scraped_at": "2025-12-03T21:23:00.943436",
    "source": "Lantern Labaton",
    "status": "Open to New Clients"
  },
  {
    "url": "https://lantern.labaton.com/case/gold-coin-group",
    "title": "Gold Coin Group - Lantern",
    "description": "[email protected]",
    "potential_recovery": "$500 or more POTENTIAL RECOVERY",
    "eligible_states": "California, New York, and Virginia",
    "date": null,
    "scraped_at": "2025-12-03T21:23:02.983835",
    "source": "Lantern Labaton",
    "status": "Open to New Clients"
  },
  {
    "url": "https://lantern.labaton.com/case/finicity",
    "title": "Finicity - Lantern",
    "description": "[email protected]",
    "potential_recovery": "$500 or more POTENTIAL RECOVERY",
    "eligible_states": "California, New York, and Virginia",
    "date": null,
    "scraped_at": "2025-12-03T21:23:05.059189",
    "source": "Lantern Labaton",
    "status": "Open to New Clients"
  },
  {
    "url": "https://lantern.labaton.com/case/vgw-holdings",
    "title": "VGW Holdings - Lantern",
    "description": "[email protected]",
    "potential_recovery": "$500 or more POTENTIAL RECOVERY",
    "eligible_states": "California, New York, and Virginia",
    "date": null,
    "scraped_at": "2025-12-03T21:23:06.882871",
    "source": "Lantern Labaton",
    "status": "Open to New Clients"
  },
  {
    "url": "https://lantern.labaton.com/case/cleo",
    "title": "Cleo - Lantern",
    "description": "[email protected]",
    "potential_recovery": "$500 or more POTENTIAL RECOVERY",
    "eligible_states": "California, New York, and Virginia",
    "date": null,
    "scraped_at": "2025-12-03T21:23:08.924664",
    "source": "Lantern Labaton",
    "status": "Open to New Clients"
  }
]